installerpro/__init__.py
installerpro/__main__.py
installerpro/core/git_utils.py
installerpro/i18n/__init__.py
installerpro/ui/__init__.py
installerpro/ui/gui.py
installerpro-4.0.0.dist-info/METADATA
installerpro-4.0.0.dist-info/WHEEL
installerpro-4.0.0.dist-info/entry_points.txt
installerpro-4.0.0.dist-info/top_level.txt
installerpro-4.0.0.dist-info/RECORD
