Metadata-Version: 2.4
Name: installerpro
Version: 4.0.0
Summary: Automatic multi-project Git environment installer
Author-email: Humberto Medina <tu-correo@example.com>
Requires-Python: >=3.9
Requires-Dist: requests>=2
Provides-Extra: dev
Requires-Dist: pytest>=8; extra == "dev"
Requires-Dist: pytest-cov; extra == "dev"
Requires-Dist: black; extra == "dev"
Requires-Dist: ruff; extra == "dev"
